wagtailmodelchooser/__init__.py
wagtailmodelchooser/edit_handlers.py
wagtailmodelchooser/views.py
wagtailmodelchooser/widgets.py
wagtailmodelchooser/__pycache__/__init__.cpython-34.pyc
wagtailmodelchooser/__pycache__/__init__.cpython-35.pyc
wagtailmodelchooser/__pycache__/__init__.cpython-36.pyc
wagtailmodelchooser/__pycache__/__init__.cpython-37.pyc
wagtailmodelchooser/__pycache__/edit_handlers.cpython-34.pyc
wagtailmodelchooser/__pycache__/edit_handlers.cpython-35.pyc
wagtailmodelchooser/__pycache__/edit_handlers.cpython-36.pyc
wagtailmodelchooser/__pycache__/edit_handlers.cpython-37.pyc
wagtailmodelchooser/__pycache__/views.cpython-34.pyc
wagtailmodelchooser/__pycache__/views.cpython-35.pyc
wagtailmodelchooser/__pycache__/views.cpython-36.pyc
wagtailmodelchooser/__pycache__/views.cpython-37.pyc
wagtailmodelchooser/__pycache__/widgets.cpython-34.pyc
wagtailmodelchooser/__pycache__/widgets.cpython-35.pyc
wagtailmodelchooser/__pycache__/widgets.cpython-36.pyc
wagtailmodelchooser/__pycache__/widgets.cpython-37.pyc
wagtailmodelchooser/locale/__init__.py
wagtailmodelchooser/locale/fr/LC_MESSAGES/django.mo
wagtailmodelchooser/locale/fr/LC_MESSAGES/django.po
wagtailmodelchooser/static/wagtailmodelchooser/js/model-chooser.js
wagtailmodelchooser/templates/wagtailmodelchooser/chooser/model_chooser.html
wagtailmodelchooser/templates/wagtailmodelchooser/chooser/model_chooser.js
wagtailmodelchooser/templates/wagtailmodelchooser/chooser/model_chosen.js
wagtailmodelchooser/templates/wagtailmodelchooser/chooser/model_results.html
wagtailmodelchooser/templates/wagtailmodelchooser/models/list.html
wagtailmodelchooser/templates/wagtailmodelchooser/widgets/model_chooser.html
wagtailmodelchooser/templatetags/__init__.py
wagtailmodelchooser/templatetags/wagtailmodelchooser_tags.py
wagtailmodelchooser/templatetags/__pycache__/__init__.cpython-34.pyc
wagtailmodelchooser/templatetags/__pycache__/__init__.cpython-35.pyc
wagtailmodelchooser/templatetags/__pycache__/__init__.cpython-36.pyc
wagtailmodelchooser-0.3.0.dist-info/LICENSE
wagtailmodelchooser-0.3.0.dist-info/METADATA
wagtailmodelchooser-0.3.0.dist-info/WHEEL
wagtailmodelchooser-0.3.0.dist-info/top_level.txt
wagtailmodelchooser-0.3.0.dist-info/RECORD
