Metadata-Version: 2.1
Name: wagtailmodelchooser
Version: 0.3.0
Summary: Wagtail chooser panel generator for generic Django models
Home-page: https://github.com/Naeka/wagtailmodelchooser
Author: Naeka
Author-email: leo@naeka.fr
License: BSD
Platform: UNKNOWN
Classifier: Development Status :: 5 - Production/Stable
Classifier: Environment :: Web Environment
Classifier: Intended Audience :: Developers
Classifier: License :: OSI Approved :: BSD License
Classifier: Operating System :: OS Independent
Classifier: Natural Language :: English
Classifier: Programming Language :: Python
Classifier: Programming Language :: Python :: 3
Classifier: Programming Language :: Python :: 3.4
Classifier: Programming Language :: Python :: 3.5
Classifier: Programming Language :: Python :: 3.6
Classifier: Programming Language :: Python :: 3.7
Classifier: Framework :: Django
Classifier: Framework :: Django :: 1.11
Classifier: Framework :: Django :: 2.0
Classifier: Framework :: Django :: 2.1
Requires-Dist: Django (<2.2,>=1.11)
Requires-Dist: wagtail (>=2.2)
Provides-Extra: docs
Requires-Dist: mkdocs (==0.11.1) ; extra == 'docs'
Provides-Extra: testing
Requires-Dist: pytest-django (<3.5,>=3.2) ; extra == 'testing'
Requires-Dist: pytest (>=3.6) ; extra == 'testing'
Requires-Dist: pytest-cov (>=2.5) ; extra == 'testing'
Requires-Dist: flake8 (>=2.4.0) ; extra == 'testing'
Requires-Dist: wheel (==0.24.0) ; extra == 'testing'
